CHANGELOG.md
LICENSE
MANIFEST.in
README.md
setup.cfg
setup.py
django_template_editor.egg-info/PKG-INFO
django_template_editor.egg-info/SOURCES.txt
django_template_editor.egg-info/dependency_links.txt
django_template_editor.egg-info/top_level.txt
editor/__init__.py
editor/app_settings.py
editor/apps.py
editor/models.py
editor/tests.py
editor/urls.py
editor/views.py
editor/frontend/dist/template-editor-bundle.js
editor/migrations/__init__.py
example/__init__.py
example/asgi.py
example/settings.py
example/urls.py
example/wsgi.py